proconip/__init__.py
proconip/api.py
proconip/definitions.py
proconip-1.4.7.dist-info/METADATA
proconip-1.4.7.dist-info/WHEEL
proconip-1.4.7.dist-info/licenses/LICENSE
proconip-1.4.7.dist-info/RECORD
