Metadata-Version: 2.3
Name: proconip
Version: 1.4.7
Summary: Library for basic interaction with the Procon.IP pool controller unit.
Project-URL: Homepage, https://github.com/ylabonte/proconip-pypi
Project-URL: Bug Tracker, https://github.com/ylabonte/proconip-pypi/issues
Author-email: Yannic Labonte <yannic.labonte@gmail.com>
License-File: LICENSE
Classifier: License :: OSI Approved :: GNU Affero General Public License v3
Classifier: Operating System :: OS Independent
Classifier: Programming Language :: Python :: 3
Requires-Python: >=3.10
